[
  {
    "id": "613100",
    "host": "1",
    "url": "https://store.steampowered.com/app/613100/House_Flipper/?snr=1_7_7_2300_150_1",
    "name": "House Flipper",
    "discount_percent": "25",
    "image": "https://steamcdn-a.akamaihd.net/steam/apps/613100/header.jpg?t=1556269061",
    "update_at": "2019-05-09T10:58:53.901Z"
  },
  {
    "id": "591370",
    "host": "3",
    "url": "https://store.steampowered.com/app/591370/Production_Line__Car_factory_simulation/?snr=1_7_7_2300_150_3",
    "name": "Production Line : Car factory simulation",
    "discount_percent": "20",
    "image": "https://steamcdn-a.akamaihd.net/steam/apps/591370/header.jpg?t=1557149071",
    "update_at": "2019-05-09T10:58:53.901Z"
  },
  {
    "id": "503560",
    "host": "3",
    "url": "https://store.steampowered.com/app/503560/911_Operator/?snr=1_7_7_2300_150_3",
    "name": "911 Operator",
    "discount_percent": "75",
    "image": "https://steamcdn-a.akamaihd.net/steam/apps/503560/header.jpg?t=1550078854",
    "update_at": "2019-05-09T10:58:53.901Z"
  },
  {
    "id": "740410",
    "host": "4",
    "url": "https://store.steampowered.com/app/740410/Puzzle_Chambers/?snr=1_7_7_2300_150_4",
    "name": "Puzzle Chambers",
    "discount_percent": "75",
    "image": "https://steamcdn-a.akamaihd.net/steam/apps/740410/header.jpg?t=1549476802",
    "update_at": "2019-05-09T10:58:53.901Z"
  },
  {
    "id": "8800",
    "host": "0",
    "url": "https://store.steampowered.com/app/8800/Civilization_IV_Beyond_the_Sword/?snr=1_7_7_2300_150_10",
    "name": "Civilization IV: Beyond the Sword",
    "discount_percent": "75",
    "image": "https://steamcdn-a.akamaihd.net/steam/apps/8800/header.jpg?t=1534463279",
    "update_at": "2019-05-09T10:58:53.901Z"
  },
  {
    "id": "890220",
    "host": "2",
    "url": "https://store.steampowered.com/app/890220/Math_Fun/?snr=1_7_7_2300_150_12",
    "name": "Math Fun",
    "discount_percent": "80",
    "image": "https://steamcdn-a.akamaihd.net/steam/apps/890220/header.jpg?t=1533404522",
    "update_at": "2019-05-09T10:58:53.901Z"
  },
  {
    "id": "251810",
    "host": "5",
    "url": "https://store.steampowered.com/app/251810/Leadwerks_Game_Engine/?snr=1_7_7_2300_150_15",
    "name": "Leadwerks Game Engine",
    "discount_percent": "80",
    "image": "https://steamcdn-a.akamaihd.net/steam/apps/251810/header.jpg?t=1552944805",
    "update_at": "2019-05-09T10:58:53.902Z"
  },
  {
    "id": "430060",
    "host": "1",
    "url": "https://store.steampowered.com/app/430060/Leadwerks_Game_Engine__Nature_Model_Pack/?snr=1_7_7_2300_150_21",
    "name": "Leadwerks Game Engine - Nature Model Pack",
    "discount_percent": "67",
    "image": "https://steamcdn-a.akamaihd.net/steam/apps/430060/header.jpg?t=1462402185",
    "update_at": "2019-05-09T10:58:53.902Z"
  },
  {
    "id": "329100",
    "host": "4",
    "url": "https://store.steampowered.com/app/329100/Leadwerks_Game_Engine__FPS_Weapons_Pack/?snr=1_7_7_2300_150_24",
    "name": "Leadwerks Game Engine - FPS Weapons Pack",
    "discount_percent": "67",
    "image": "https://steamcdn-a.akamaihd.net/steam/apps/329100/header.jpg?t=1462402147",
    "update_at": "2019-05-09T10:58:53.902Z"
  },
  {
    "id": "321142",
    "host": "5",
    "url": "https://store.steampowered.com/app/321142/GameGuru_Mega_Pack_3/?snr=1_7_7_2300_150_25",
    "name": "GameGuru Mega Pack 3",
    "discount_percent": "60",
    "image": "https://steamcdn-a.akamaihd.net/steam/apps/321142/header.jpg?t=1535479727",
    "update_at": "2019-05-09T10:58:53.902Z"
  },
  {
    "id": "347400",
    "host": "8",
    "url": "https://store.steampowered.com/app/347400/001_Game_Creator/?snr=1_7_7_2300_150_28",
    "name": "001 Game Creator",
    "discount_percent": "60",
    "image": "https://steamcdn-a.akamaihd.net/steam/apps/347400/header.jpg?t=1555944944",
    "update_at": "2019-05-09T10:58:53.902Z"
  },
  {
    "id": "468820",
    "host": "9",
    "url": "https://store.steampowered.com/app/468820/Titans_of_Space_PLUS/?snr=1_7_7_2300_150_29",
    "name": "Titans of Space PLUS",
    "discount_percent": "50",
    "image": "https://steamcdn-a.akamaihd.net/steam/apps/468820/header.jpg?t=1556327877",
    "update_at": "2019-05-09T10:58:53.902Z"
  },
  {
    "id": "410530",
    "host": "2",
    "url": "https://store.steampowered.com/app/410530/AppGameKit__Giant_Asset_Pack_1/?snr=1_7_7_2300_150_32",
    "name": "AppGameKit - Giant Asset Pack 1",
    "discount_percent": "60",
    "image": "https://steamcdn-a.akamaihd.net/steam/apps/410530/header.jpg?t=1556632034",
    "update_at": "2019-05-09T10:58:53.902Z"
  },
  {
    "id": "345300",
    "host": "3",
    "url": "https://store.steampowered.com/app/345300/Wildlife_Creative_Studio/?snr=1_7_7_2300_150_33",
    "name": "Wildlife Creative Studio",
    "discount_percent": "50",
    "image": "https://steamcdn-a.akamaihd.net/steam/apps/345300/header.jpg?t=1510310362",
    "update_at": "2019-05-09T10:58:53.902Z"
  },
  {
    "id": "822010",
    "host": "3",
    "url": "https://store.steampowered.com/app/822010/GameGuru__Melee_Weapons_Pack/?snr=1_7_7_2300_150_33",
    "name": "GameGuru - Melee Weapons Pack",
    "discount_percent": "50",
    "image": "https://steamcdn-a.akamaihd.net/steam/apps/822010/header.jpg?t=1535479810",
    "update_at": "2019-05-09T10:58:53.902Z"
  },
  {
    "id": "822010",
    "host": "4",
    "url": "https://store.steampowered.com/app/822010/GameGuru__Melee_Weapons_Pack/?snr=1_7_7_2300_150_34",
    "name": "GameGuru - Melee Weapons Pack",
    "discount_percent": "50",
    "image": "https://steamcdn-a.akamaihd.net/steam/apps/822010/header.jpg?t=1535479810",
    "update_at": "2019-05-09T10:58:53.902Z"
  },
  {
    "id": "995560",
    "host": "4",
    "url": "https://store.steampowered.com/app/995560/Zombies_for_S2ENGINE_HD/?snr=1_7_7_2300_150_34",
    "name": "Zombies for S2ENGINE HD",
    "discount_percent": "50",
    "image": "https://steamcdn-a.akamaihd.net/steam/apps/995560/header.jpg?t=1545217218",
    "update_at": "2019-05-09T10:58:53.902Z"
  },
  {
    "id": "747520",
    "host": "4",
    "url": "https://store.steampowered.com/app/747520/S2ENGINE_HD__Building_Generator/?snr=1_7_7_2300_150_34",
    "name": "S2ENGINE HD - Building Generator",
    "discount_percent": "50",
    "image": "https://steamcdn-a.akamaihd.net/steam/apps/747520/header.jpg?t=1544006412",
    "update_at": "2019-05-09T10:58:53.902Z"
  },
  {
    "id": "430061",
    "host": "5",
    "url": "https://store.steampowered.com/app/430061/Leadwerks_Game_Engine__The_Zone/?snr=1_7_7_2300_150_35",
    "name": "Leadwerks Game Engine - The Zone",
    "discount_percent": "50",
    "image": "https://steamcdn-a.akamaihd.net/steam/apps/430061/header.jpg?t=1513960260",
    "update_at": "2019-05-09T10:58:53.902Z"
  },
  {
    "id": "469670",
    "host": "6",
    "url": "https://store.steampowered.com/app/469670/Leadwerks_Game_Engine__Mercenary_Action_Figure/?snr=1_7_7_2300_150_36",
    "name": "Leadwerks Game Engine - Mercenary Action Figure",
    "discount_percent": "50",
    "image": "https://steamcdn-a.akamaihd.net/steam/apps/469670/header.jpg?t=1479867235",
    "update_at": "2019-05-09T10:58:53.902Z"
  },
  {
    "id": "469670",
    "host": "7",
    "url": "https://store.steampowered.com/app/469670/Leadwerks_Game_Engine__Mercenary_Action_Figure/?snr=1_7_7_2300_150_37",
    "name": "Leadwerks Game Engine - Mercenary Action Figure",
    "discount_percent": "50",
    "image": "https://steamcdn-a.akamaihd.net/steam/apps/469670/header.jpg?t=1479867235",
    "update_at": "2019-05-09T10:58:53.902Z"
  },
  {
    "id": "266310",
    "host": "0",
    "url": "https://store.steampowered.com/app/266310/GameGuru/?snr=1_7_7_2300_150_40",
    "name": "GameGuru",
    "discount_percent": "50",
    "image": "https://steamcdn-a.akamaihd.net/steam/apps/266310/header.jpg?t=1556926808",
    "update_at": "2019-05-09T10:58:53.902Z"
  },
  {
    "id": "315490",
    "host": "3",
    "url": "https://store.steampowered.com/app/315490/Leadwerks_Game_Engine__SciFi_Interior_Model_Pack/?snr=1_7_7_2300_150_43",
    "name": "Leadwerks Game Engine - SciFi Interior Model Pack",
    "discount_percent": "50",
    "image": "https://steamcdn-a.akamaihd.net/steam/apps/315490/header.jpg?t=1462402108",
    "update_at": "2019-05-09T10:58:53.902Z"
  },
  {
    "id": "345310",
    "host": "3",
    "url": "https://store.steampowered.com/app/345310/My_Family_Creative_Studio/?snr=1_7_7_2300_150_43",
    "name": "My Family Creative Studio",
    "discount_percent": "50",
    "image": "https://steamcdn-a.akamaihd.net/steam/apps/345310/header.jpg?t=1510310303",
    "update_at": "2019-05-09T10:58:53.902Z"
  },
  {
    "id": "365440",
    "host": "3",
    "url": "https://store.steampowered.com/app/365440/Platfinity/?snr=1_7_7_2300_150_43",
    "name": "Platfinity™",
    "discount_percent": "50",
    "image": "https://steamcdn-a.akamaihd.net/steam/apps/365440/header.jpg?t=1535571179",
    "update_at": "2019-05-09T10:58:53.902Z"
  },
  {
    "id": "335580",
    "host": "3",
    "url": "https://store.steampowered.com/app/335580/Leadwerks_Game_Engine__Zombie_Action_Figures/?snr=1_7_7_2300_150_43",
    "name": "Leadwerks Game Engine - Zombie Action Figures",
    "discount_percent": "50",
    "image": "https://steamcdn-a.akamaihd.net/steam/apps/335580/header.jpg?t=1462402075",
    "update_at": "2019-05-09T10:58:53.903Z"
  },
  {
    "id": "345720",
    "host": "6",
    "url": "https://store.steampowered.com/app/345720/The_Official_AppGameKit_Tutorial_Guide_Vol_1/?snr=1_7_7_2300_150_46",
    "name": "The Official AppGameKit Tutorial Guide Vol 1",
    "discount_percent": "40",
    "image": "https://steamcdn-a.akamaihd.net/steam/apps/345720/header.jpg?t=1556632209",
    "update_at": "2019-05-09T10:58:53.903Z"
  },
  {
    "id": "787710",
    "host": "7",
    "url": "https://store.steampowered.com/app/787710/Comrades_and_Barons_Solitaire_of_Bloody_1919/?snr=1_7_7_2300_150_47",
    "name": "Comrades and Barons: Solitaire of Bloody 1919",
    "discount_percent": "40",
    "image": "https://steamcdn-a.akamaihd.net/steam/apps/787710/header.jpg?t=1549824474",
    "update_at": "2019-05-09T10:58:53.903Z"
  },
  {
    "id": "567360",
    "host": "3",
    "url": "https://store.steampowered.com/app/567360/001_Game_Creator__Point__Click_Adventure_Kit/?snr=1_7_7_2300_150_53",
    "name": "001 Game Creator - Point & Click Adventure Kit",
    "discount_percent": "30",
    "image": "https://steamcdn-a.akamaihd.net/steam/apps/567360/header.jpg?t=1544877692",
    "update_at": "2019-05-09T10:58:53.903Z"
  },
  {
    "id": "564681",
    "host": "3",
    "url": "https://store.steampowered.com/app/564681/001_Game_Creator__3D_FPS__Survival_Horror_Kit/?snr=1_7_7_2300_150_53",
    "name": "001 Game Creator - 3D FPS / Survival Horror Kit",
    "discount_percent": "30",
    "image": "https://steamcdn-a.akamaihd.net/steam/apps/564681/header.jpg?t=1544877529",
    "update_at": "2019-05-09T10:58:53.903Z"
  },
  {
    "id": "564680",
    "host": "3",
    "url": "https://store.steampowered.com/app/564680/001_Game_Creator__MMORPG_Kit/?snr=1_7_7_2300_150_53",
    "name": "001 Game Creator - MMORPG Kit",
    "discount_percent": "30",
    "image": "https://steamcdn-a.akamaihd.net/steam/apps/564680/header.jpg?t=1544877372",
    "update_at": "2019-05-09T10:58:53.903Z"
  },
  {
    "id": "907510",
    "host": "3",
    "url": "https://store.steampowered.com/app/907510/GameGuru__Enhanced_Weapons_Pack/?snr=1_7_7_2300_150_53",
    "name": "GameGuru - Enhanced Weapons Pack",
    "discount_percent": "30",
    "image": "https://steamcdn-a.akamaihd.net/steam/apps/907510/header.jpg?t=1532536327",
    "update_at": "2019-05-09T10:58:53.903Z"
  },
  {
    "id": "996910",
    "host": "3",
    "url": "https://store.steampowered.com/app/996910/GameGuru__Cold_War_Pack/?snr=1_7_7_2300_150_53",
    "name": "GameGuru - Cold War Pack",
    "discount_percent": "30",
    "image": "https://steamcdn-a.akamaihd.net/steam/apps/996910/header.jpg?t=1544631321",
    "update_at": "2019-05-09T10:58:53.903Z"
  },
  {
    "id": "767240",
    "host": "3",
    "url": "https://store.steampowered.com/app/767240/BASIC8/?snr=1_7_7_2300_150_53",
    "name": "BASIC8",
    "discount_percent": "35",
    "image": "https://steamcdn-a.akamaihd.net/steam/apps/767240/header.jpg?t=1544695321",
    "update_at": "2019-05-09T10:58:53.903Z"
  },
  {
    "id": "943190",
    "host": "7",
    "url": "https://store.steampowered.com/app/943190/OCTOPTICOM/?snr=1_7_7_2300_150_57",
    "name": "OCTOPTICOM",
    "discount_percent": "25",
    "image": "https://steamcdn-a.akamaihd.net/steam/apps/943190/header.jpg?t=1547821716",
    "update_at": "2019-05-09T10:58:53.903Z"
  },
  {
    "id": "1007440",
    "host": "0",
    "url": "https://store.steampowered.com/app/1007440/Solitaire_Learn_Chemistry/?snr=1_7_7_2300_150_60",
    "name": "Solitaire: Learn Chemistry",
    "discount_percent": "30",
    "image": "https://steamcdn-a.akamaihd.net/steam/apps/1007440/header.jpg?t=1555498184",
    "update_at": "2019-05-09T10:58:53.903Z"
  },
  {
    "id": "962250",
    "host": "0",
    "url": "https://store.steampowered.com/app/962250/Solitaire_Learn_the_Flags/?snr=1_7_7_2300_150_60",
    "name": "Solitaire: Learn the Flags!",
    "discount_percent": "30",
    "image": "https://steamcdn-a.akamaihd.net/steam/apps/962250/header.jpg?t=1550566685",
    "update_at": "2019-05-09T10:58:53.903Z"
  },
  {
    "id": "997720",
    "host": "1",
    "url": "https://store.steampowered.com/app/997720/Lets_Learn_Japanese_Hiragana/?snr=1_7_7_2300_150_61",
    "name": "Let's Learn Japanese! Hiragana",
    "discount_percent": "20",
    "image": "https://steamcdn-a.akamaihd.net/steam/apps/997720/header.jpg?t=1551344770",
    "update_at": "2019-05-09T10:58:53.903Z"
  },
  {
    "id": "677150",
    "host": "1",
    "url": "https://store.steampowered.com/app/677150/RPG_World__Forgotten_Lands/?snr=1_7_7_2300_150_61",
    "name": "RPG World - Forgotten Lands",
    "discount_percent": "20",
    "image": "https://steamcdn-a.akamaihd.net/steam/apps/677150/header.jpg?t=1533328018",
    "update_at": "2019-05-09T10:58:53.903Z"
  },
  {
    "id": "997720",
    "host": "2",
    "url": "https://store.steampowered.com/app/997720/Lets_Learn_Japanese_Hiragana/?snr=1_7_7_2300_150_62",
    "name": "Let's Learn Japanese! Hiragana",
    "discount_percent": "20",
    "image": "https://steamcdn-a.akamaihd.net/steam/apps/997720/header.jpg?t=1551344770",
    "update_at": "2019-05-09T10:58:53.903Z"
  },
  {
    "id": "877850",
    "host": "8",
    "url": "https://store.steampowered.com/app/877850/TribeXR_DJ_School/?snr=1_7_7_2300_150_68",
    "name": "TribeXR DJ School",
    "discount_percent": "10",
    "image": "https://steamcdn-a.akamaihd.net/steam/apps/877850/header.jpg?t=1556066993",
    "update_at": "2019-05-09T10:58:53.903Z"
  },
  {
    "id": "322410",
    "host": "3",
    "url": "https://store.steampowered.com/app/322410/Bin_Weevils_Arty_Arcade/?snr=1_7_7_2300_150_83",
    "name": "Bin Weevils Arty Arcade",
    "discount_percent": "50",
    "image": "https://steamcdn-a.akamaihd.net/steam/apps/322410/header.jpg?t=1510309872",
    "update_at": "2019-05-09T10:58:53.903Z"
  },
  {
    "id": "977250",
    "host": "2",
    "url": "https://store.steampowered.com/app/977250/001_Game_Creator__Enhanced_RPG_TurnBased_Battles/?snr=1_7_7_2300_150_92",
    "name": "001 Game Creator - Enhanced RPG (Turn-Based Battles)",
    "discount_percent": "15",
    "image": "https://steamcdn-a.akamaihd.net/steam/apps/977250/header.jpg?t=1544877584",
    "update_at": "2019-05-09T10:58:53.903Z"
  },
  {
    "id": "951950",
    "host": "2",
    "url": "https://store.steampowered.com/app/951950/001_Game_Creator__Retro_Fantasy_Music_Pack_Volume_1/?snr=1_7_7_2300_150_92",
    "name": "001 Game Creator - Retro Fantasy Music Pack Volume 1",
    "discount_percent": "15",
    "image": "https://steamcdn-a.akamaihd.net/steam/apps/951950/header.jpg?t=1544877633",
    "update_at": "2019-05-09T10:58:53.903Z"
  }
]