[
  {
    "id": "368370",
    "host": "3",
    "url": "https://store.steampowered.com/app/368370/Her_Story/?snr=1_7_7_2300_150_3",
    "name": "Her Story",
    "discount_percent": "60",
    "image": "https://steamcdn-a.akamaihd.net/steam/apps/368370/header.jpg?t=1479954872",
    "update_at": "2019-05-09T10:58:09.677Z"
  },
  {
    "id": "218640",
    "host": "3",
    "url": "https://store.steampowered.com/app/218640/Lucius/?snr=1_7_7_2300_150_3",
    "name": "Lucius",
    "discount_percent": "85",
    "image": "https://steamcdn-a.akamaihd.net/steam/apps/218640/header.jpg?t=1535010582",
    "update_at": "2019-05-09T10:58:09.677Z"
  },
  {
    "id": "214340",
    "host": "3",
    "url": "https://store.steampowered.com/app/214340/Deponia/?snr=1_7_7_2300_150_3",
    "name": "Deponia",
    "discount_percent": "90",
    "image": "https://steamcdn-a.akamaihd.net/steam/apps/214340/header.jpg?t=1550763265",
    "update_at": "2019-05-09T10:58:09.677Z"
  },
  {
    "id": "950990",
    "host": "5",
    "url": "https://store.steampowered.com/app/950990/Business_Magnate/?snr=1_7_7_2300_150_5",
    "name": "Business Magnate",
    "discount_percent": "25",
    "image": "https://steamcdn-a.akamaihd.net/steam/apps/950990/header.jpg?t=1556883581",
    "update_at": "2019-05-09T10:58:09.677Z"
  },
  {
    "id": "792040",
    "host": "5",
    "url": "https://store.steampowered.com/app/792040/Detective_Di_The_Silk_Rose_Murders/?snr=1_7_7_2300_150_5",
    "name": "Detective Di: The Silk Rose Murders | 狄仁杰之锦蔷薇",
    "discount_percent": "10",
    "image": "https://steamcdn-a.akamaihd.net/steam/apps/792040/header.jpg?t=1556774073",
    "update_at": "2019-05-09T10:58:09.677Z"
  },
  {
    "id": "255300",
    "host": "7",
    "url": "https://store.steampowered.com/app/255300/Journey_of_a_Roach/?snr=1_7_7_2300_150_7",
    "name": "Journey of a Roach",
    "discount_percent": "86",
    "image": "https://steamcdn-a.akamaihd.net/steam/apps/255300/header.jpg?t=1524052015",
    "update_at": "2019-05-09T10:58:09.677Z"
  },
  {
    "id": "203830",
    "host": "7",
    "url": "https://store.steampowered.com/app/203830/The_Dark_Eye_Chains_of_Satinav/?snr=1_7_7_2300_150_7",
    "name": "The Dark Eye: Chains of Satinav",
    "discount_percent": "90",
    "image": "https://steamcdn-a.akamaihd.net/steam/apps/203830/header.jpg?t=1524045417",
    "update_at": "2019-05-09T10:58:09.677Z"
  },
  {
    "id": "219910",
    "host": "7",
    "url": "https://store.steampowered.com/app/219910/Edna__Harvey_Harveys_New_Eyes/?snr=1_7_7_2300_150_7",
    "name": "Edna & Harvey: Harvey's New Eyes",
    "discount_percent": "90",
    "image": "https://steamcdn-a.akamaihd.net/steam/apps/219910/header.jpg?t=1524052454",
    "update_at": "2019-05-09T10:58:09.677Z"
  },
  {
    "id": "230820",
    "host": "7",
    "url": "https://store.steampowered.com/app/230820/The_Night_of_the_Rabbit/?snr=1_7_7_2300_150_7",
    "name": "The Night of the Rabbit",
    "discount_percent": "90",
    "image": "https://steamcdn-a.akamaihd.net/steam/apps/230820/header.jpg?t=1524052332",
    "update_at": "2019-05-09T10:58:09.677Z"
  },
  {
    "id": "243200",
    "host": "7",
    "url": "https://store.steampowered.com/app/243200/Memoria/?snr=1_7_7_2300_150_7",
    "name": "Memoria",
    "discount_percent": "90",
    "image": "https://steamcdn-a.akamaihd.net/steam/apps/243200/header.jpg?t=1479205240",
    "update_at": "2019-05-09T10:58:09.677Z"
  },
  {
    "id": "349140",
    "host": "9",
    "url": "https://store.steampowered.com/app/349140/Corrosion_Cold_Winter_Waiting_Enhanced_Edition/?snr=1_7_7_2300_150_9",
    "name": "Corrosion: Cold Winter Waiting [Enhanced Edition]",
    "discount_percent": "90",
    "image": "https://steamcdn-a.akamaihd.net/steam/apps/349140/header.jpg?t=1459213219",
    "update_at": "2019-05-09T10:58:09.677Z"
  },
  {
    "id": "46510",
    "host": "9",
    "url": "https://store.steampowered.com/app/46510/Syberia_II/?snr=1_7_7_2300_150_9",
    "name": "Syberia II",
    "discount_percent": "80",
    "image": "https://steamcdn-a.akamaihd.net/steam/apps/46510/header.jpg?t=1554900911",
    "update_at": "2019-05-09T10:58:09.677Z"
  },
  {
    "id": "46500",
    "host": "9",
    "url": "https://store.steampowered.com/app/46500/Syberia/?snr=1_7_7_2300_150_9",
    "name": "Syberia",
    "discount_percent": "80",
    "image": "https://steamcdn-a.akamaihd.net/steam/apps/46500/header.jpg?t=1554900806",
    "update_at": "2019-05-09T10:58:09.677Z"
  },
  {
    "id": "713680",
    "host": "1",
    "url": "https://store.steampowered.com/app/713680/Ablepsia/?snr=1_7_7_2300_150_11",
    "name": "Ablepsia",
    "discount_percent": "90",
    "image": "https://steamcdn-a.akamaihd.net/steam/apps/713680/header.jpg?t=1524492435",
    "update_at": "2019-05-09T10:58:09.677Z"
  },
  {
    "id": "451570",
    "host": "3",
    "url": "https://store.steampowered.com/app/451570/Demetrios__The_BIG_Cynical_Adventure/?snr=1_7_7_2300_150_13",
    "name": "Demetrios - The BIG Cynical Adventure",
    "discount_percent": "75",
    "image": "https://steamcdn-a.akamaihd.net/steam/apps/451570/header.jpg?t=1550570665",
    "update_at": "2019-05-09T10:58:09.677Z"
  },
  {
    "id": "299160",
    "host": "5",
    "url": "https://store.steampowered.com/app/299160/Empress_Of_The_Deep_2_Song_Of_The_Blue_Whale/?snr=1_7_7_2300_150_15",
    "name": "Empress Of The Deep 2: Song Of The Blue Whale",
    "discount_percent": "80",
    "image": "https://steamcdn-a.akamaihd.net/steam/apps/299160/header.jpg?t=1447361722",
    "update_at": "2019-05-09T10:58:09.677Z"
  },
  {
    "id": "481490",
    "host": "5",
    "url": "https://store.steampowered.com/app/481490/Demetrios__Original_Soundtrack/?snr=1_7_7_2300_150_15",
    "name": "Demetrios - Original Soundtrack",
    "discount_percent": "75",
    "image": "https://steamcdn-a.akamaihd.net/steam/apps/481490/header.jpg?t=1464710938",
    "update_at": "2019-05-09T10:58:09.677Z"
  },
  {
    "id": "363330",
    "host": "6",
    "url": "https://store.steampowered.com/app/363330/Mind_Snares_Alices_Journey/?snr=1_7_7_2300_150_16",
    "name": "Mind Snares: Alice's Journey",
    "discount_percent": "70",
    "image": "https://steamcdn-a.akamaihd.net/steam/apps/363330/header.jpg?t=1530538923",
    "update_at": "2019-05-09T10:58:09.677Z"
  },
  {
    "id": "613470",
    "host": "6",
    "url": "https://store.steampowered.com/app/613470/The_Inner_World__The_Last_Wind_Monk/?snr=1_7_7_2300_150_16",
    "name": "The Inner World - The Last Wind Monk",
    "discount_percent": "70",
    "image": "https://steamcdn-a.akamaihd.net/steam/apps/613470/header.jpg?t=1540479337",
    "update_at": "2019-05-09T10:58:09.677Z"
  },
  {
    "id": "414660",
    "host": "6",
    "url": "https://store.steampowered.com/app/414660/Vampire_Legends_The_True_Story_of_Kisilova/?snr=1_7_7_2300_150_16",
    "name": "Vampire Legends: The True Story of Kisilova",
    "discount_percent": "70",
    "image": "https://steamcdn-a.akamaihd.net/steam/apps/414660/header.jpg?t=1530539039",
    "update_at": "2019-05-09T10:58:09.677Z"
  },
  {
    "id": "420060",
    "host": "7",
    "url": "https://store.steampowered.com/app/420060/Candle/?snr=1_7_7_2300_150_17",
    "name": "Candle",
    "discount_percent": "67",
    "image": "https://steamcdn-a.akamaihd.net/steam/apps/420060/header.jpg?t=1523465131",
    "update_at": "2019-05-09T10:58:09.677Z"
  },
  {
    "id": "561770",
    "host": "9",
    "url": "https://store.steampowered.com/app/561770/Just_Ignore_Them/?snr=1_7_7_2300_150_19",
    "name": "Just Ignore Them",
    "discount_percent": "75",
    "image": "https://steamcdn-a.akamaihd.net/steam/apps/561770/header.jpg?t=1549558400",
    "update_at": "2019-05-09T10:58:09.677Z"
  },
  {
    "id": "382140",
    "host": "9",
    "url": "https://store.steampowered.com/app/382140/SKYHILL/?snr=1_7_7_2300_150_19",
    "name": "SKYHILL",
    "discount_percent": "75",
    "image": "https://steamcdn-a.akamaihd.net/steam/apps/382140/header.jpg?t=1556187796",
    "update_at": "2019-05-09T10:58:09.677Z"
  },
  {
    "id": "319970",
    "host": "9",
    "url": "https://store.steampowered.com/app/319970/The_Detail/?snr=1_7_7_2300_150_19",
    "name": "The Detail",
    "discount_percent": "75",
    "image": "https://steamcdn-a.akamaihd.net/steam/apps/319970/header.jpg?t=1529997401",
    "update_at": "2019-05-09T10:58:09.677Z"
  },
  {
    "id": "869300",
    "host": "0",
    "url": "https://store.steampowered.com/app/869300/The_Darkest_Woods/?snr=1_7_7_2300_150_20",
    "name": "The Darkest Woods",
    "discount_percent": "70",
    "image": "https://steamcdn-a.akamaihd.net/steam/apps/869300/header.jpg?t=1542453364",
    "update_at": "2019-05-09T10:58:09.677Z"
  },
  {
    "id": "448440",
    "host": "3",
    "url": "https://store.steampowered.com/app/448440/Bizarre_Earthquake/?snr=1_7_7_2300_150_23",
    "name": "Bizarre Earthquake",
    "discount_percent": "74",
    "image": "https://steamcdn-a.akamaihd.net/steam/apps/448440/header.jpg?t=1499594929",
    "update_at": "2019-05-09T10:58:09.677Z"
  },
  {
    "id": "706490",
    "host": "3",
    "url": "https://store.steampowered.com/app/706490/Little_hidden_city/?snr=1_7_7_2300_150_23",
    "name": "Little hidden city",
    "discount_percent": "74",
    "image": "https://steamcdn-a.akamaihd.net/steam/apps/706490/header.jpg?t=1530509166",
    "update_at": "2019-05-09T10:58:09.677Z"
  },
  {
    "id": "317030",
    "host": "4",
    "url": "https://store.steampowered.com/app/317030/Fatty_Bears_Birthday_Surprise/?snr=1_7_7_2300_150_24",
    "name": "Fatty Bear's Birthday Surprise",
    "discount_percent": "60",
    "image": "https://steamcdn-a.akamaihd.net/steam/apps/317030/header.jpg?t=1554426146",
    "update_at": "2019-05-09T10:58:09.677Z"
  },
  {
    "id": "392280",
    "host": "4",
    "url": "https://store.steampowered.com/app/392280/The_Franz_Kafka_Videogame/?snr=1_7_7_2300_150_24",
    "name": "The Franz Kafka Videogame",
    "discount_percent": "72",
    "image": "https://steamcdn-a.akamaihd.net/steam/apps/392280/header.jpg?t=1540971640",
    "update_at": "2019-05-09T10:58:09.677Z"
  },
  {
    "id": "458470",
    "host": "4",
    "url": "https://store.steampowered.com/app/458470/Grim_Legends_3_The_Dark_City/?snr=1_7_7_2300_150_24",
    "name": "Grim Legends 3: The Dark City",
    "discount_percent": "60",
    "image": "https://steamcdn-a.akamaihd.net/steam/apps/458470/header.jpg?t=1530538889",
    "update_at": "2019-05-09T10:58:09.677Z"
  },
  {
    "id": "350010",
    "host": "5",
    "url": "https://store.steampowered.com/app/350010/Time_Mysteries_Inheritance__Remastered/?snr=1_7_7_2300_150_25",
    "name": "Time Mysteries: Inheritance - Remastered",
    "discount_percent": "70",
    "image": "https://steamcdn-a.akamaihd.net/steam/apps/350010/header.jpg?t=1530539033",
    "update_at": "2019-05-09T10:58:09.677Z"
  },
  {
    "id": "464340",
    "host": "5",
    "url": "https://store.steampowered.com/app/464340/Syberia_3/?snr=1_7_7_2300_150_25",
    "name": "Syberia 3",
    "discount_percent": "70",
    "image": "https://steamcdn-a.akamaihd.net/steam/apps/464340/header.jpg?t=1554900634",
    "update_at": "2019-05-09T10:58:09.677Z"
  },
  {
    "id": "752330",
    "host": "6",
    "url": "https://store.steampowered.com/app/752330/Shape_of_America_Episode_One/?snr=1_7_7_2300_150_26",
    "name": "Shape of America: Episode One",
    "discount_percent": "60",
    "image": "https://steamcdn-a.akamaihd.net/steam/apps/752330/header.jpg?t=1530611236",
    "update_at": "2019-05-09T10:58:09.677Z"
  },
  {
    "id": "747050",
    "host": "7",
    "url": "https://store.steampowered.com/app/747050/Portal_Journey_Portarius/?snr=1_7_7_2300_150_27",
    "name": "Portal Journey: Portarius",
    "discount_percent": "59",
    "image": "https://steamcdn-a.akamaihd.net/steam/apps/747050/header.jpg?t=1529599061",
    "update_at": "2019-05-09T10:58:09.677Z"
  },
  {
    "id": "574260",
    "host": "8",
    "url": "https://store.steampowered.com/app/574260/The_Secret_Order_5_The_Buried_Kingdom/?snr=1_7_7_2300_150_28",
    "name": "The Secret Order 5: The Buried Kingdom",
    "discount_percent": "60",
    "image": "https://steamcdn-a.akamaihd.net/steam/apps/574260/header.jpg?t=1530539019",
    "update_at": "2019-05-09T10:58:09.677Z"
  },
  {
    "id": "898780",
    "host": "9",
    "url": "https://store.steampowered.com/app/898780/Escape_Game/?snr=1_7_7_2300_150_29",
    "name": "Escape Game",
    "discount_percent": "50",
    "image": "https://steamcdn-a.akamaihd.net/steam/apps/898780/header.jpg?t=1551109128",
    "update_at": "2019-05-09T10:58:09.677Z"
  },
  {
    "id": "813540",
    "host": "9",
    "url": "https://store.steampowered.com/app/813540/Scheming_Through_The_Zombie_Apocalypse_The_Beginning/?snr=1_7_7_2300_150_29",
    "name": "Scheming Through The Zombie Apocalypse: The Beginning",
    "discount_percent": "50",
    "image": "https://steamcdn-a.akamaihd.net/steam/apps/813540/header.jpg?t=1549555601",
    "update_at": "2019-05-09T10:58:09.677Z"
  },
  {
    "id": "677020",
    "host": "0",
    "url": "https://store.steampowered.com/app/677020/Eventide_3_Legacy_of_Legends/?snr=1_7_7_2300_150_30",
    "name": "Eventide 3: Legacy of Legends",
    "discount_percent": "50",
    "image": "https://steamcdn-a.akamaihd.net/steam/apps/677020/header.jpg?t=1511418501",
    "update_at": "2019-05-09T10:58:09.677Z"
  },
  {
    "id": "354240",
    "host": "0",
    "url": "https://store.steampowered.com/app/354240/Please_Dont_Touch_Anything/?snr=1_7_7_2300_150_30",
    "name": "Please, Don’t Touch Anything",
    "discount_percent": "50",
    "image": "https://steamcdn-a.akamaihd.net/steam/apps/354240/header.jpg?t=1498065674",
    "update_at": "2019-05-09T10:58:09.677Z"
  },
  {
    "id": "384170",
    "host": "3",
    "url": "https://store.steampowered.com/app/384170/The_Soundtrack_of_Tremendous_Corporation/?snr=1_7_7_2300_150_33",
    "name": "The Soundtrack of Tremendous Corporation",
    "discount_percent": "50",
    "image": "https://steamcdn-a.akamaihd.net/steam/apps/384170/header.jpg?t=1530026164",
    "update_at": "2019-05-09T10:58:09.677Z"
  },
  {
    "id": "384171",
    "host": "4",
    "url": "https://store.steampowered.com/app/384171/The_Secret_of_Tremendous_Corporation_DLC/?snr=1_7_7_2300_150_34",
    "name": "The Secret of Tremendous Corporation: DLC",
    "discount_percent": "50",
    "image": "https://steamcdn-a.akamaihd.net/steam/apps/384171/header.jpg?t=1530026150",
    "update_at": "2019-05-09T10:58:09.677Z"
  },
  {
    "id": "353790",
    "host": "5",
    "url": "https://store.steampowered.com/app/353790/Spud/?snr=1_7_7_2300_150_35",
    "name": "Spud!",
    "discount_percent": "50",
    "image": "https://steamcdn-a.akamaihd.net/steam/apps/353790/header.jpg?t=1510310520",
    "update_at": "2019-05-09T10:58:09.677Z"
  },
  {
    "id": "971120",
    "host": "6",
    "url": "https://store.steampowered.com/app/971120/Forgiveness__Escape_Room/?snr=1_7_7_2300_150_36",
    "name": "Forgiveness : Escape Room",
    "discount_percent": "50",
    "image": "https://steamcdn-a.akamaihd.net/steam/apps/971120/header.jpg?t=1557101396",
    "update_at": "2019-05-09T10:58:09.677Z"
  },
  {
    "id": "840700",
    "host": "6",
    "url": "https://store.steampowered.com/app/840700/Qvabllock/?snr=1_7_7_2300_150_36",
    "name": "Qvabllock",
    "discount_percent": "50",
    "image": "https://steamcdn-a.akamaihd.net/steam/apps/840700/header.jpg?t=1526648736",
    "update_at": "2019-05-09T10:58:09.677Z"
  },
  {
    "id": "971120",
    "host": "7",
    "url": "https://store.steampowered.com/app/971120/Forgiveness__Escape_Room/?snr=1_7_7_2300_150_37",
    "name": "Forgiveness : Escape Room",
    "discount_percent": "50",
    "image": "https://steamcdn-a.akamaihd.net/steam/apps/971120/header.jpg?t=1557101396",
    "update_at": "2019-05-09T10:58:09.677Z"
  },
  {
    "id": "840700",
    "host": "7",
    "url": "https://store.steampowered.com/app/840700/Qvabllock/?snr=1_7_7_2300_150_37",
    "name": "Qvabllock",
    "discount_percent": "50",
    "image": "https://steamcdn-a.akamaihd.net/steam/apps/840700/header.jpg?t=1526648736",
    "update_at": "2019-05-09T10:58:09.677Z"
  },
  {
    "id": "345290",
    "host": "9",
    "url": "https://store.steampowered.com/app/345290/The_Quivering/?snr=1_7_7_2300_150_39",
    "name": "The Quivering",
    "discount_percent": "50",
    "image": "https://steamcdn-a.akamaihd.net/steam/apps/345290/header.jpg?t=1521451332",
    "update_at": "2019-05-09T10:58:09.677Z"
  },
  {
    "id": "746840",
    "host": "9",
    "url": "https://store.steampowered.com/app/746840/Chronicles_of_Magic_Divided_Kingdoms/?snr=1_7_7_2300_150_39",
    "name": "Chronicles of Magic: Divided Kingdoms",
    "discount_percent": "50",
    "image": "https://steamcdn-a.akamaihd.net/steam/apps/746840/header.jpg?t=1548311936",
    "update_at": "2019-05-09T10:58:09.677Z"
  },
  {
    "id": "336730",
    "host": "3",
    "url": "https://store.steampowered.com/app/336730/Supreme_League_of_Patriots__Episode_3_Ice_Cold_in_Ellis/?snr=1_7_7_2300_150_43",
    "name": "Supreme League of Patriots - Episode 3: Ice Cold in Ellis",
    "discount_percent": "50",
    "image": "https://steamcdn-a.akamaihd.net/steam/apps/336730/header.jpg?t=1478025856",
    "update_at": "2019-05-09T10:58:09.677Z"
  },
  {
    "id": "872090",
    "host": "4",
    "url": "https://store.steampowered.com/app/872090/Freezeer/?snr=1_7_7_2300_150_44",
    "name": "Freezeer",
    "discount_percent": "50",
    "image": "https://steamcdn-a.akamaihd.net/steam/apps/872090/header.jpg?t=1529570604",
    "update_at": "2019-05-09T10:58:09.677Z"
  },
  {
    "id": "444580",
    "host": "4",
    "url": "https://store.steampowered.com/app/444580/ALONE_IN_SPACE/?snr=1_7_7_2300_150_44",
    "name": "ALONE IN SPACE",
    "discount_percent": "50",
    "image": "https://steamcdn-a.akamaihd.net/steam/apps/444580/header.jpg?t=1503302565",
    "update_at": "2019-05-09T10:58:09.677Z"
  },
  {
    "id": "582280",
    "host": "4",
    "url": "https://store.steampowered.com/app/582280/PIGMENTUM/?snr=1_7_7_2300_150_44",
    "name": "PIGMENTUM",
    "discount_percent": "50",
    "image": "https://steamcdn-a.akamaihd.net/steam/apps/582280/header.jpg?t=1546229771",
    "update_at": "2019-05-09T10:58:09.677Z"
  },
  {
    "id": "872090",
    "host": "5",
    "url": "https://store.steampowered.com/app/872090/Freezeer/?snr=1_7_7_2300_150_45",
    "name": "Freezeer",
    "discount_percent": "50",
    "image": "https://steamcdn-a.akamaihd.net/steam/apps/872090/header.jpg?t=1529570604",
    "update_at": "2019-05-09T10:58:09.677Z"
  },
  {
    "id": "550990",
    "host": "6",
    "url": "https://store.steampowered.com/app/550990/Viktor_a_Steampunk_Adventure/?snr=1_7_7_2300_150_46",
    "name": "Viktor, a Steampunk Adventure",
    "discount_percent": "40",
    "image": "https://steamcdn-a.akamaihd.net/steam/apps/550990/header.jpg?t=1489831615",
    "update_at": "2019-05-09T10:58:09.677Z"
  },
  {
    "id": "761480",
    "host": "6",
    "url": "https://store.steampowered.com/app/761480/Snail_Trek__Chapter_3_Lettuce_Be/?snr=1_7_7_2300_150_46",
    "name": "Snail Trek - Chapter 3: Lettuce Be",
    "discount_percent": "40",
    "image": "https://steamcdn-a.akamaihd.net/steam/apps/761480/header.jpg?t=1547349810",
    "update_at": "2019-05-09T10:58:09.677Z"
  },
  {
    "id": "550990",
    "host": "7",
    "url": "https://store.steampowered.com/app/550990/Viktor_a_Steampunk_Adventure/?snr=1_7_7_2300_150_47",
    "name": "Viktor, a Steampunk Adventure",
    "discount_percent": "40",
    "image": "https://steamcdn-a.akamaihd.net/steam/apps/550990/header.jpg?t=1489831615",
    "update_at": "2019-05-09T10:58:09.677Z"
  },
  {
    "id": "502750",
    "host": "7",
    "url": "https://store.steampowered.com/app/502750/Quest_for_Glory_15/?snr=1_7_7_2300_150_47",
    "name": "Quest for Glory 1-5",
    "discount_percent": "35",
    "image": "https://steamcdn-a.akamaihd.net/steam/apps/502750/header.jpg?t=1472524232",
    "update_at": "2019-05-09T10:58:09.677Z"
  },
  {
    "id": "775960",
    "host": "7",
    "url": "https://store.steampowered.com/app/775960/The_Tower_of_Beatrice/?snr=1_7_7_2300_150_47",
    "name": "The Tower of Beatrice",
    "discount_percent": "40",
    "image": "https://steamcdn-a.akamaihd.net/steam/apps/775960/header.jpg?t=1552124165",
    "update_at": "2019-05-09T10:58:09.677Z"
  },
  {
    "id": "502750",
    "host": "8",
    "url": "https://store.steampowered.com/app/502750/Quest_for_Glory_15/?snr=1_7_7_2300_150_48",
    "name": "Quest for Glory 1-5",
    "discount_percent": "35",
    "image": "https://steamcdn-a.akamaihd.net/steam/apps/502750/header.jpg?t=1472524232",
    "update_at": "2019-05-09T10:58:09.677Z"
  },
  {
    "id": "654080",
    "host": "4",
    "url": "https://store.steampowered.com/app/654080/Der_einzig_wahre_Auserwhlte/?snr=1_7_7_2300_150_54",
    "name": "Der einzig wahre Auserwählte",
    "discount_percent": "30",
    "image": "https://steamcdn-a.akamaihd.net/steam/apps/654080/header.jpg?t=1555055119",
    "update_at": "2019-05-09T10:58:09.677Z"
  },
  {
    "id": "922700",
    "host": "4",
    "url": "https://store.steampowered.com/app/922700/Hidden_Animals__Photo_Hunt_Seek_and_Find_Game/?snr=1_7_7_2300_150_54",
    "name": "Hidden Animals : Photo Hunt. Seek and Find Game",
    "discount_percent": "30",
    "image": "https://steamcdn-a.akamaihd.net/steam/apps/922700/header.jpg?t=1539923605",
    "update_at": "2019-05-09T10:58:09.677Z"
  },
  {
    "id": "818860",
    "host": "4",
    "url": "https://store.steampowered.com/app/818860/Beyond_the_Sky/?snr=1_7_7_2300_150_54",
    "name": "Beyond the Sky",
    "discount_percent": "30",
    "image": "https://steamcdn-a.akamaihd.net/steam/apps/818860/header.jpg?t=1549674371",
    "update_at": "2019-05-09T10:58:09.677Z"
  },
  {
    "id": "698450",
    "host": "7",
    "url": "https://store.steampowered.com/app/698450/Midnight_Quest/?snr=1_7_7_2300_150_57",
    "name": "Midnight Quest",
    "discount_percent": "25",
    "image": "https://steamcdn-a.akamaihd.net/steam/apps/698450/header.jpg?t=1527640191",
    "update_at": "2019-05-09T10:58:09.677Z"
  },
  {
    "id": "715650",
    "host": "8",
    "url": "https://store.steampowered.com/app/715650/The_Endless_Journey/?snr=1_7_7_2300_150_58",
    "name": "The Endless Journey",
    "discount_percent": "20",
    "image": "https://steamcdn-a.akamaihd.net/steam/apps/715650/header.jpg?t=1549535241",
    "update_at": "2019-05-09T10:58:09.677Z"
  },
  {
    "id": "611760",
    "host": "2",
    "url": "https://store.steampowered.com/app/611760/Dont_Escape_4_Days_to_Survive/?snr=1_7_7_2300_150_62",
    "name": "Don't Escape: 4 Days to Survive",
    "discount_percent": "15",
    "image": "https://steamcdn-a.akamaihd.net/steam/apps/611760/header.jpg?t=1556559780",
    "update_at": "2019-05-09T10:58:09.677Z"
  },
  {
    "id": "1008910",
    "host": "4",
    "url": "https://store.steampowered.com/app/1008910/_Sadboy/?snr=1_7_7_2300_150_64",
    "name": "心塞男孩 Sadboy",
    "discount_percent": "20",
    "image": "https://steamcdn-a.akamaihd.net/steam/apps/1008910/header.jpg?t=1548256651",
    "update_at": "2019-05-09T10:58:09.677Z"
  },
  {
    "id": "1026080",
    "host": "4",
    "url": "https://store.steampowered.com/app/1026080/The_Antidote/?snr=1_7_7_2300_150_64",
    "name": "The Antidote",
    "discount_percent": "25",
    "image": "https://steamcdn-a.akamaihd.net/steam/apps/1026080/header.jpg?t=1554103902",
    "update_at": "2019-05-09T10:58:09.677Z"
  },
  {
    "id": "364350",
    "host": "7",
    "url": "https://store.steampowered.com/app/364350/The_Apotheosis_Project/?snr=1_7_7_2300_150_67",
    "name": "The Apotheosis Project",
    "discount_percent": "20",
    "image": "https://steamcdn-a.akamaihd.net/steam/apps/364350/header.jpg?t=1540795647",
    "update_at": "2019-05-09T10:58:09.677Z"
  },
  {
    "id": "395250",
    "host": "7",
    "url": "https://store.steampowered.com/app/395250/The_Adventures_of_Fatman/?snr=1_7_7_2300_150_67",
    "name": "The Adventures of Fatman",
    "discount_percent": "20",
    "image": "https://steamcdn-a.akamaihd.net/steam/apps/395250/header.jpg?t=1540795643",
    "update_at": "2019-05-09T10:58:09.677Z"
  },
  {
    "id": "966660",
    "host": "8",
    "url": "https://store.steampowered.com/app/966660/Invisible_Fist/?snr=1_7_7_2300_150_68",
    "name": "Invisible Fist",
    "discount_percent": "10",
    "image": "https://steamcdn-a.akamaihd.net/steam/apps/966660/header.jpg?t=1557152499",
    "update_at": "2019-05-09T10:58:09.677Z"
  },
  {
    "id": "476880",
    "host": "3",
    "url": "https://store.steampowered.com/app/476880/Rescue_Lucy/?snr=1_7_7_2300_150_73",
    "name": "Rescue Lucy",
    "discount_percent": "85",
    "image": "https://steamcdn-a.akamaihd.net/steam/apps/476880/header.jpg?t=1548506104",
    "update_at": "2019-05-09T10:58:09.677Z"
  },
  {
    "id": "489780",
    "host": "8",
    "url": "https://store.steampowered.com/app/489780/Demetrios__Artbook/?snr=1_7_7_2300_150_78",
    "name": "Demetrios - Artbook",
    "discount_percent": "75",
    "image": "https://steamcdn-a.akamaihd.net/steam/apps/489780/header.jpg?t=1478027838",
    "update_at": "2019-05-09T10:58:09.677Z"
  },
  {
    "id": "336020",
    "host": "9",
    "url": "https://store.steampowered.com/app/336020/Pahelika_Secret_Legends/?snr=1_7_7_2300_150_79",
    "name": "Pahelika: Secret Legends",
    "discount_percent": "50",
    "image": "https://steamcdn-a.akamaihd.net/steam/apps/336020/header.jpg?t=1447365595",
    "update_at": "2019-05-09T10:58:09.677Z"
  },
  {
    "id": "508810",
    "host": "9",
    "url": "https://store.steampowered.com/app/508810/A_Tale_of_Caos_Overture__OST/?snr=1_7_7_2300_150_79",
    "name": "A Tale of Caos: Overture - OST",
    "discount_percent": "70",
    "image": "https://steamcdn-a.akamaihd.net/steam/apps/508810/header.jpg?t=1551900178",
    "update_at": "2019-05-09T10:58:09.677Z"
  },
  {
    "id": "981270",
    "host": "2",
    "url": "https://store.steampowered.com/app/981270/Runas_School_Story/?snr=1_7_7_2300_150_92",
    "name": "Runa's School Story",
    "discount_percent": "15",
    "image": "https://steamcdn-a.akamaihd.net/steam/apps/981270/header.jpg?t=1557104412",
    "update_at": "2019-05-09T10:58:09.677Z"
  }
]