{
  "0": {
    "link": "https://store.steampowered.com/app/501220/Space_Ribbon/?snr=1_7_7_2300_150_11",
    "name": "Space Ribbon",
    "title": "Save 90% on Space Ribbon on Steam",
    "image": "https://steamcdn-a.akamaihd.net/steam/apps/501220/header.jpg?t=1549320412",
    "tags": [
      "Simulation",
      "Casual",
      "Racing",
      "Space",
      "Great Soundtrack",
      "4 Player Local",
      "VR",
      "Procedural Generation",
      "Psychedelic",
      "Sports",
      "Action",
      "Indie",
      "Competitive",
      "Sci-fi",
      "Futuristic",
      "Family Friendly",
      "Singleplayer",
      "Real-Time",
      "Atmospheric",
      "Split Screen",
      "+"
    ]
  },
  "1": {
    "link": "https://store.steampowered.com/app/515650/Straimium_Immortaly/?snr=1_7_7_2300_150_37",
    "name": "Straimium Immortaly",
    "title": "Save 45% on Straimium Immortaly on Steam",
    "image": "https://steamcdn-a.akamaihd.net/steam/apps/515650/header.jpg?t=1550767663",
    "tags": [
      "Indie",
      "Action",
      "Dungeon Crawler",
      "Bullet Hell",
      "Difficult",
      "Rogue-like",
      "Rogue-lite",
      "Shoot 'Em Up",
      "Replay Value",
      "Pixel Graphics",
      "Great Soundtrack",
      "Procedural Generation",
      "Shooter",
      "Perma Death",
      "Atmospheric",
      "2D",
      "Psychedelic",
      "Ninja",
      "+"
    ]
  },
  "2": {
    "link": "https://store.steampowered.com/app/961220/Sanatorium_Purgatorium/?snr=1_7_7_2300_150_41",
    "name": "Sanatorium Purgatorium",
    "title": "Save 44% on Sanatorium Purgatorium on Steam",
    "image": "https://steamcdn-a.akamaihd.net/steam/apps/961220/header.jpg?t=1541036146",
    "tags": [
      "Sexual Content",
      "Nudity",
      "Gore",
      "Indie",
      "Casual",
      "Violent",
      "Visual Novel",
      "Anime",
      "2D",
      "Psychedelic",
      "Psychological Horror",
      "Story Rich",
      "Atmospheric",
      "Horror",
      "Dark",
      "Addictive",
      "Relaxing",
      "Great Soundtrack",
      "+"
    ]
  },
  "3": {
    "link": "https://store.steampowered.com/app/558450/Fibrillation_HD/?snr=1_7_7_2300_150_50",
    "name": "Fibrillation HD",
    "title": "Save 30% on Fibrillation HD on Steam",
    "image": "https://steamcdn-a.akamaihd.net/steam/apps/558450/header.jpg?t=1543962482",
    "tags": [
      "Adventure",
      "Indie",
      "Exploration",
      "Horror",
      "Violent",
      "First-Person",
      "Walking Simulator",
      "Surreal",
      "Abstract",
      "Atmospheric",
      "Philisophical",
      "Singleplayer",
      "Short",
      "Psychedelic",
      "Mystery",
      "Dark",
      "+"
    ]
  },
  "4": {
    "link": "https://store.steampowered.com/app/399140/Straima/?snr=1_7_7_2300_150_50",
    "name": "Straima",
    "title": "Save 35% on Straima on Steam",
    "image": "https://steamcdn-a.akamaihd.net/steam/apps/399140/header.jpg?t=1547113569",
    "tags": [
      "Indie",
      "Action",
      "Platformer",
      "Difficult",
      "Fast-Paced",
      "Co-op",
      "2D",
      "Pixel Graphics",
      "Local Co-Op",
      "Local Multiplayer",
      "Level Editor",
      "Multiplayer",
      "Psychedelic",
      "Colorful",
      "Retro",
      "Arcade",
      "Great Soundtrack",
      "4 Player Local",
      "Ninja",
      "Singleplayer",
      "+"
    ]
  },
  "5": {
    "link": "https://store.steampowered.com/app/536690/AENTITY/?snr=1_7_7_2300_150_57",
    "name": "AENTITY",
    "title": "Save 25% on AENTITY on Steam",
    "image": "https://steamcdn-a.akamaihd.net/steam/apps/536690/header.jpg?t=1554976601",
    "tags": [
      "Surreal",
      "Relaxing",
      "Psychedelic",
      "Nonlinear",
      "Colorful",
      "Mystery",
      "Experience",
      "Experimental",
      "Stylized",
      "Atmospheric",
      "Philisophical",
      "Design & Illustration",
      "Utilities",
      "Software",
      "Animation & Modeling",
      "+"
    ]
  },
  "6": {
    "link": "https://store.steampowered.com/app/536690/AENTITY/?snr=1_7_7_2300_150_58",
    "name": "AENTITY",
    "title": "Save 25% on AENTITY on Steam",
    "image": "https://steamcdn-a.akamaihd.net/steam/apps/536690/header.jpg?t=1554976601",
    "tags": [
      "Surreal",
      "Relaxing",
      "Psychedelic",
      "Nonlinear",
      "Colorful",
      "Mystery",
      "Experience",
      "Experimental",
      "Stylized",
      "Atmospheric",
      "Philisophical",
      "Design & Illustration",
      "Utilities",
      "Software",
      "Animation & Modeling",
      "+"
    ]
  },
  "7": {
    "link": "https://store.steampowered.com/app/334710/Ilamentia/?snr=1_7_7_2300_150_67",
    "name": "Ilamentia",
    "title": "Save 15% on Ilamentia on Steam",
    "image": "https://steamcdn-a.akamaihd.net/steam/apps/334710/header.jpg?t=1547113692",
    "tags": [
      "Indie",
      "Puzzle",
      "First-Person",
      "Surreal",
      "Psychedelic",
      "Exploration",
      "Colorful",
      "Atmospheric",
      "Abstract",
      "Mystery",
      "Sci-fi",
      "Great Soundtrack",
      "Action",
      "Psychological",
      "Difficult",
      "Adventure",
      "Illuminati",
      "GameMaker",
      "+"
    ]
  },
  "8": {
    "link": "https://store.steampowered.com/app/662240/Epitasis/?snr=1_7_7_2300_150_68",
    "name": "Epitasis",
    "title": "Save 10% on Epitasis on Steam",
    "image": "https://steamcdn-a.akamaihd.net/steam/apps/662240/header.jpg?t=1557101065",
    "tags": [
      "Adventure",
      "Indie",
      "Action",
      "Puzzle",
      "Great Soundtrack",
      "Exploration",
      "Open World",
      "Sci-fi",
      "Space",
      "Surreal",
      "Psychedelic",
      "Atmospheric",
      "First-Person",
      "Singleplayer",
      "Nonlinear",
      "Science",
      "Mystery",
      "Relaxing",
      "Crowdfunded",
      "Casual",
      "+"
    ]
  },
  "9": {
    "link": "https://store.steampowered.com/app/1037620/Epitasis_Original_Soundtrack/?snr=1_7_7_2300_150_92",
    "name": "Epitasis Original Soundtrack",
    "title": "Save 10% on Epitasis Original Soundtrack on Steam",
    "image": "https://steamcdn-a.akamaihd.net/steam/apps/1037620/header.jpg?t=1556719265",
    "tags": [
      "Action",
      "Adventure",
      "Indie",
      "Great Soundtrack",
      "Psychedelic",
      "Sci-fi",
      "Soundtrack",
      "Atmospheric",
      "Exploration",
      "Beautiful",
      "Crowdfunded",
      "Colorful",
      "+"
    ]
  },
  "10": {
    "link": "https://store.steampowered.com/app/1029890/Layers_of_Fear_2/?snr=1_7_7_2300_150_93",
    "name": "Layers of Fear 2",
    "title": "Save 10% on Layers of Fear 2 on Steam",
    "image": "https://steamcdn-a.akamaihd.net/steam/apps/1029890/header.jpg?t=1557174707",
    "tags": [
      "Psychological Horror",
      "Singleplayer",
      "Atmospheric",
      "Psychological",
      "Story Rich",
      "Dark",
      "Exploration",
      "Walking Simulator",
      "Puzzle",
      "Drama",
      "Beautiful",
      "Great Soundtrack",
      "Mature",
      "Choices Matter",
      "Masterpiece",
      "Surreal",
      "Sequel",
      "First-Person",
      "Psychedelic",
      "Indie",
      "+"
    ]
  },
  "Date": "5/8/2019, 5:57:36 PM"
}