{
  "0": {
    "link": "https://store.steampowered.com/app/208580/STAR_WARS_Knights_of_the_Old_Republic_II__The_Sith_Lords/?snr=1_7_7_2300_150_2",
    "name": "STAR WARS™ Knights of the Old Republic™ II - The Sith Lords™",
    "title": "Save 65% on STAR WARS™ Knights of the Old Republic™ II - The Sith Lords™ on Steam",
    "image": "https://steamcdn-a.akamaihd.net/steam/apps/208580/header.jpg?t=1545238520",
    "tags": [
      "RPG",
      "Star Wars",
      "Story Rich",
      "Sci-fi",
      "Singleplayer",
      "Classic",
      "Real-Time with Pause",
      "Adventure",
      "Party-Based RPG",
      "Choices Matter",
      "Moddable",
      "Character Customization",
      "Third Person",
      "Multiple Endings",
      "Space",
      "Masterpiece",
      "Female Protagonist",
      "Atmospheric",
      "Action",
      "Turn-Based Combat",
      "+"
    ]
  },
  "1": {
    "link": "https://store.steampowered.com/app/32370/STAR_WARS__Knights_of_the_Old_Republic/?snr=1_7_7_2300_150_2",
    "name": "STAR WARS™ - Knights of the Old Republic™",
    "title": "Save 65% on STAR WARS™ - Knights of the Old Republic™ on Steam",
    "image": "https://steamcdn-a.akamaihd.net/steam/apps/32370/header.jpg?t=1545238521",
    "tags": [
      "RPG",
      "Star Wars",
      "Sci-fi",
      "Story Rich",
      "Singleplayer",
      "Classic",
      "Masterpiece",
      "Party-Based RPG",
      "Adventure",
      "Real-Time with Pause",
      "Third Person",
      "Action",
      "Choices Matter",
      "Exploration",
      "Fantasy",
      "Space",
      "Atmospheric",
      "Turn-Based",
      "Moddable",
      "Great Soundtrack",
      "+"
    ]
  },
  "2": {
    "link": "https://store.steampowered.com/app/235380/Blitzkrieg_3/?snr=1_7_7_2300_150_3",
    "name": "Blitzkrieg 3",
    "title": "Save 50% on Blitzkrieg 3 on Steam",
    "image": "https://steamcdn-a.akamaihd.net/steam/apps/235380/header.jpg?t=1547539591",
    "tags": [
      "Strategy",
      "World War II",
      "RTS",
      "Military",
      "War",
      "Tactical",
      "Real Time Tactics",
      "Multiplayer",
      "Historical",
      "Tanks",
      "PvP",
      "Massively Multiplayer",
      "Singleplayer",
      "Competitive",
      "Early Access",
      "Simulation",
      "Realistic",
      "Difficult",
      "Real-Time",
      "Real-Time with Pause",
      "+"
    ]
  },
  "3": {
    "link": "https://store.steampowered.com/app/243950/Divinity_Dragon_Commander/?snr=1_7_7_2300_150_3",
    "name": "Divinity: Dragon Commander",
    "title": "Save 90% on Divinity: Dragon Commander on Steam",
    "image": "https://steamcdn-a.akamaihd.net/steam/apps/243950/header.jpg?t=1447357292",
    "tags": [
      "Strategy",
      "RPG",
      "Dragons",
      "Fantasy",
      "Political",
      "Action",
      "RTS",
      "Singleplayer",
      "Steampunk",
      "Turn-Based",
      "Choices Matter",
      "Real-Time with Pause",
      "Story Rich",
      "Multiplayer",
      "Comedy",
      "Co-op",
      "Masterpiece",
      "Great Soundtrack",
      "+"
    ]
  },
  "4": {
    "link": "https://store.steampowered.com/app/214170/Divine_Divinity/?snr=1_7_7_2300_150_4",
    "name": "Divine Divinity",
    "title": "Save 75% on Divine Divinity on Steam",
    "image": "https://steamcdn-a.akamaihd.net/steam/apps/214170/header.jpg?t=1447355993",
    "tags": [
      "RPG",
      "Fantasy",
      "Isometric",
      "Classic",
      "Action RPG",
      "Open World",
      "Singleplayer",
      "Real-Time with Pause",
      "Hack and Slash",
      "Adventure",
      "Exploration",
      "Action",
      "2D",
      "CRPG",
      "Great Soundtrack",
      "Funny",
      "Female Protagonist",
      "Atmospheric",
      "Masterpiece",
      "Story Rich",
      "+"
    ]
  },
  "5": {
    "link": "https://store.steampowered.com/app/950990/Business_Magnate/?snr=1_7_7_2300_150_5",
    "name": "Business Magnate",
    "title": "Save 25% on Business Magnate on Steam",
    "image": "https://steamcdn-a.akamaihd.net/steam/apps/950990/header.jpg?t=1556883581",
    "tags": [
      "Simulation",
      "Strategy",
      "Management",
      "Economy",
      "Resource Management",
      "Sandbox",
      "Singleplayer",
      "Building",
      "Indie",
      "Casual",
      "Real-Time with Pause",
      "Isometric",
      "Point & Click",
      "+"
    ]
  },
  "6": {
    "link": "https://store.steampowered.com/app/227760/March_of_the_Eagles/?snr=1_7_7_2300_150_18",
    "name": "March of the Eagles",
    "title": "Save 80% on March of the Eagles on Steam",
    "image": "https://steamcdn-a.akamaihd.net/steam/apps/227760/header.jpg?t=1530640646",
    "tags": [
      "Strategy",
      "Grand Strategy",
      "Simulation",
      "Historical",
      "Real-Time with Pause",
      "Sandbox",
      "+"
    ]
  },
  "7": {
    "link": "https://store.steampowered.com/app/403970/The_Dwarves/?snr=1_7_7_2300_150_19",
    "name": "The Dwarves",
    "title": "Save 75% on The Dwarves on Steam",
    "image": "https://steamcdn-a.akamaihd.net/steam/apps/403970/header.jpg?t=1489400983",
    "tags": [
      "RPG",
      "Fantasy",
      "Real-Time with Pause",
      "Tactical RPG",
      "Kickstarter",
      "Adventure",
      "Open World",
      "Story Rich",
      "Singleplayer",
      "Great Soundtrack",
      "Action",
      "+"
    ]
  },
  "8": {
    "link": "https://store.steampowered.com/app/643960/Cursed_Treasure_2/?snr=1_7_7_2300_150_29",
    "name": "Cursed Treasure 2",
    "title": "Save 50% on Cursed Treasure 2 on Steam",
    "image": "https://steamcdn-a.akamaihd.net/steam/apps/643960/header.jpg?t=1511185920",
    "tags": [
      "Indie",
      "Strategy",
      "Tower Defense",
      "2D",
      "Real-Time",
      "RTS",
      "Real-Time with Pause",
      "Singleplayer",
      "Fantasy",
      "Top-Down",
      "Cult Classic",
      "Replay Value",
      "Resource Management",
      "+"
    ]
  },
  "9": {
    "link": "https://store.steampowered.com/app/291650/Pillars_of_Eternity/?snr=1_7_7_2300_150_41",
    "name": "Pillars of Eternity",
    "title": "Save 40% on Pillars of Eternity on Steam",
    "image": "https://steamcdn-a.akamaihd.net/steam/apps/291650/header.jpg?t=1552039638",
    "tags": [
      "RPG",
      "Fantasy",
      "Isometric",
      "Story Rich",
      "Singleplayer",
      "CRPG",
      "Party-Based RPG",
      "Real-Time with Pause",
      "Kickstarter",
      "Adventure",
      "Atmospheric",
      "Dark Fantasy",
      "Open World",
      "Exploration",
      "Classic",
      "Character Customization",
      "Strategy",
      "Great Soundtrack",
      "Indie",
      "Crowdfunded",
      "+"
    ]
  },
  "10": {
    "link": "https://store.steampowered.com/app/833890/NeoSticks/?snr=1_7_7_2300_150_65",
    "name": "NeoSticks",
    "title": "Save 15% on NeoSticks on Steam",
    "image": "https://steamcdn-a.akamaihd.net/steam/apps/833890/header.jpg?t=1524208713",
    "tags": [
      "Indie",
      "Atmospheric",
      "Relaxing",
      "Simulation",
      "Strategy",
      "Anime",
      "Funny",
      "Top-Down",
      "Side Scroller",
      "Tutorial",
      "Addictive",
      "Choices Matter",
      "Singleplayer",
      "Minimalist",
      "Difficult",
      "Action",
      "Clicker",
      "Real-Time with Pause",
      "Competitive",
      "Family Friendly",
      "+"
    ]
  },
  "11": {
    "link": "https://store.steampowered.com/app/989560/NeoGeometry/?snr=1_7_7_2300_150_67",
    "name": "NeoGeometry",
    "title": "Save 15% on NeoGeometry on Steam",
    "image": "https://steamcdn-a.akamaihd.net/steam/apps/989560/header.jpg?t=1549276662",
    "tags": [
      "Indie",
      "Strategy",
      "Minimalist",
      "Atmospheric",
      "Relaxing",
      "Anime",
      "Funny",
      "Simulation",
      "Top-Down",
      "Tutorial",
      "Addictive",
      "Choices Matter",
      "Singleplayer",
      "Difficult",
      "Action",
      "Family Friendly",
      "Competitive",
      "Real-Time with Pause",
      "Side Scroller",
      "+"
    ]
  },
  "12": {
    "link": "https://store.steampowered.com/app/718220/NeoBoom2/?snr=1_7_7_2300_150_70",
    "name": "NeoBoom2",
    "title": "Save 15% on NeoBoom2 on Steam",
    "image": "https://steamcdn-a.akamaihd.net/steam/apps/718220/header.jpg?t=1509470204",
    "tags": [
      "Indie",
      "Strategy",
      "Relaxing",
      "Singleplayer",
      "Open World",
      "Clicker",
      "Action",
      "Difficult",
      "Minimalist",
      "Choices Matter",
      "Addictive",
      "Tutorial",
      "Atmospheric",
      "Side Scroller",
      "Top-Down",
      "Funny",
      "Simulation",
      "Real-Time with Pause",
      "Anime",
      "Great Soundtrack",
      "+"
    ]
  },
  "13": {
    "link": "https://store.steampowered.com/app/771610/NeoBalls/?snr=1_7_7_2300_150_70",
    "name": "NeoBalls",
    "title": "Save 15% on NeoBalls on Steam",
    "image": "https://steamcdn-a.akamaihd.net/steam/apps/771610/header.jpg?t=1514985370",
    "tags": [
      "Indie",
      "Anime",
      "Open World",
      "Great Soundtrack",
      "Clicker",
      "Addictive",
      "Atmospheric",
      "Relaxing",
      "Simulation",
      "Strategy",
      "Funny",
      "Top-Down",
      "Side Scroller",
      "Tutorial",
      "Choices Matter",
      "Singleplayer",
      "Minimalist",
      "Difficult",
      "Action",
      "Real-Time with Pause",
      "+"
    ]
  },
  "14": {
    "link": "https://store.steampowered.com/app/786560/NeoBalls2/?snr=1_7_7_2300_150_88",
    "name": "NeoBalls2",
    "title": "Save 15% on NeoBalls2 on Steam",
    "image": "https://steamcdn-a.akamaihd.net/steam/apps/786560/header.jpg?t=1518679600",
    "tags": [
      "Indie",
      "Atmospheric",
      "Strategy",
      "Funny",
      "Side Scroller",
      "Tutorial",
      "Singleplayer",
      "Addictive",
      "Difficult",
      "Minimalist",
      "Simulation",
      "Real-Time with Pause",
      "Clicker",
      "Relaxing",
      "Action",
      "Choices Matter",
      "Great Soundtrack",
      "Competitive",
      "Anime",
      "+"
    ]
  },
  "15": {
    "link": "https://store.steampowered.com/app/876910/Aquarium_Simulator/?snr=1_7_7_2300_150_90",
    "name": "Aquarium Simulator",
    "title": "Save 15% on Aquarium Simulator on Steam",
    "image": "https://steamcdn-a.akamaihd.net/steam/apps/876910/header.jpg?t=1529645112",
    "tags": [
      "Simulation",
      "Indie",
      "Relaxing",
      "Singleplayer",
      "Family Friendly",
      "Atmospheric",
      "Side Scroller",
      "Tutorial",
      "Addictive",
      "Minimalist",
      "Real-Time with Pause",
      "Clicker",
      "Difficult",
      "Funny",
      "Great Soundtrack",
      "Strategy",
      "Action",
      "Choices Matter",
      "Top-Down",
      "Anime",
      "+"
    ]
  },
  "Date": "\"5/8/2019, 5:44:28 PM\""
}